[
  {
    "name": "Minyak Goreng Kemasan",
    "unit": "Rp / 620ml",
    "prices": {
      "1": 9560,
      "2": 9560,
      "3": 9571,
      "4": 9571,
      "5": 9571,
      "8": 9571,
      "9": 9629,
      "10": 9633,
      "11": 9635,
      "12": 9634,
      "15": 9631,
      "16": 9631,
      "18": 9628,
      "19": 9643,
      "22": 9646,
      "23": 9646,
      "24": 9650,
      "25": 9659,
      "26": 9659
    }
  },
  {
    "name": "Minyak Goreng Curah",
    "unit": "Rp / kg",
    "prices": {
      "1": 10628,
      "2": 10617,
      "3": 10654,
      "4": 10656,
      "5": 10645,
      "8": 10635,
      "9": 10635,
      "10": 10647,
      "11": 10632,
      "12": 10607,
      "15": 10605,
      "16": 10666,
      "18": 10663,
      "19": 10672,
      "22": 10680,
      "23": 10680,
      "24": 10677,
      "25": 10677,
      "26": 10679
    }
  },
  {
    "name": "Daging Sapi",
    "unit": "Rp / kg",
    "prices": {
      "1": 70748,
      "2": 71343,
      "3": 71431,
      "4": 71483,
      "5": 71287,
      "8": 71227,
      "9": 71399,
      "10": 71102,
      "11": 70999,
      "12": 71163,
      "15": 71217,
      "16": 70674,
      "18": 70629,
      "19": 70849,
      "22": 70794,
      "23": 70741,
      "24": 71168,
      "25": 71484,
      "26": 71734
    }
  },
  {
    "name": "Daging Ayam Broiler",
    "unit": "Rp / kg",
    "prices": {
      "1": 27592,
      "2": 27631,
      "3": 27218,
      "4": 27300,
      "5": 27265,
      "8": 27159,
      "9": 27097,
      "10": 26559,
      "11": 26427,
      "12": 26160,
      "15": 26107,
      "16": 26120,
      "18": 25917,
      "19": 25923,
      "22": 26013,
      "23": 26017,
      "24": 26040,
      "25": 26176,
      "26": 26184
    }
  },
  {
    "name": "Daging Ayam Kampung",
    "unit": "Rp / kg",
    "prices": {
      "1": 46583,
      "2": 46844,
      "3": 47573,
      "4": 46793,
      "5": 46638,
      "8": 46561,
      "9": 46772,
      "10": 46903,
      "11": 46876,
      "12": 46894,
      "15": 46907,
      "16": 46453,
      "18": 46448,
      "19": 46451,
      "22": 46439,
      "23": 46548,
      "24": 46401,
      "25": 46460,
      "26": 46648
    }
  },
  {
    "name": "Telur Ayam Ras",
    "unit": "Rp / kg",
    "prices": {
      "1": 18650,
      "2": 18677,
      "3": 18664,
      "4": 18599,
      "5": 18590,
      "8": 18742,
      "9": 18668,
      "10": 18666,
      "11": 18560,
      "12": 18477,
      "15": 18340,
      "16": 18379,
      "18": 18274,
      "19": 18185,
      "22": 18201,
      "23": 18526,
      "24": 18604,
      "25": 18656,
      "26": 18815
    }
  },
  {
    "name": "Telur Ayam Kampung",
    "unit": "Rp / kg",
    "prices": {
      "1": 36132,
      "2": 36119,
      "3": 36490,
      "4": 36496,
      "5": 36658,
      "8": 36486,
      "9": 36557,
      "10": 36687,
      "11": 36430,
      "12": 36438,
      "15": 36341,
      "16": 36198,
      "18": 36150,
      "19": 36351,
      "22": 36262,
      "23": 36262,
      "24": 36080,
      "25": 36143,
      "26": 36100
    }
  },
  {
    "name": "Tepung Terigu",
    "unit": "Rp / kg",
    "prices": {
      "1": 7581,
      "2": 7583,
      "3": 7584,
      "4": 7551,
      "5": 7551,
      "8": 7579,
      "9": 7610,
      "10": 7610,
      "11": 7655,
      "12": 7654,
      "15": 7636,
      "16": 7605,
      "18": 7603,
      "19": 7609,
      "22": 7620,
      "23": 7614,
      "24": 7600,
      "25": 7595,
      "26": 7592
    }
  },
  {
    "name": "Kedelai Impor",
    "unit": "Rp / kg",
    "prices": {
      "1": 8398,
      "2": 8398,
      "3": 8394,
      "4": 8394,
      "5": 8398,
      "8": 8396,
      "9": 8398,
      "10": 8397,
      "11": 8388,
      "12": 8369,
      "15": 8362,
      "16": 8364,
      "18": 8364,
      "19": 8339,
      "22": 8351,
      "23": 8354,
      "24": 8350,
      "25": 8353,
      "26": 8353
    }
  },
  {
    "name": "Kedelai lokal",
    "unit": "Rp / kg",
    "prices": {
      "1": 8794,
      "2": 8794,
      "3": 8780,
      "4": 8780,
      "5": 8787,
      "8": 8787,
      "9": 8783,
      "10": 8789,
      "11": 8789,
      "12": 8789,
      "15": 8789,
      "16": 8761,
      "18": 8774,
      "19": 8782,
      "22": 8843,
      "23": 8797,
      "24": 8796,
      "25": 8801,
      "26": 8806
    }
  },
  {
    "name": "Beras Medium",
    "unit": "Rp / kg",
    "prices": {
      "1": 7422,
      "2": 7427,
      "3": 7418,
      "4": 7419,
      "5": 7419,
      "8": 7436,
      "9": 7402,
      "10": 7397,
      "11": 7388,
      "12": 7414,
      "15": 7412,
      "16": 7416,
      "18": 7418,
      "19": 7418,
      "22": 7426,
      "23": 7426,
      "24": 7429,
      "25": 7458,
      "26": 7450
    }
  },
  {
    "name": "Gula Pasir",
    "unit": "Rp / kg",
    "prices": {
      "1": 10622,
      "2": 10602,
      "3": 10589,
      "4": 10572,
      "5": 10583,
      "8": 10544,
      "9": 10518,
      "10": 10607,
      "11": 10522,
      "12": 10476,
      "15": 10479,
      "16": 10461,
      "18": 10460,
      "19": 10460,
      "22": 10458,
      "23": 10455,
      "24": 10460,
      "25": 10472,
      "26": 10489
    }
  },
  {
    "name": "Susu Kental Manis",
    "unit": "Rp / 397g",
    "prices": {
      "1": 8596,
      "2": 8600,
      "3": 8631,
      "4": 8632,
      "5": 8639,
      "8": 8639,
      "9": 8639,
      "10": 8635,
      "11": 8636,
      "12": 8636,
      "15": 8638,
      "16": 8647,
      "18": 8647,
      "19": 8641,
      "22": 8641,
      "23": 8641,
      "24": 8640,
      "25": 8638,
      "26": 8641
    }
  },
  {
    "name": "Mie Instant",
    "unit": "Rp / Bungkus",
    "prices": {
      "1": 1493,
      "2": 1493,
      "3": 1493,
      "4": 1493,
      "5": 1496,
      "8": 1496,
      "9": 1496,
      "10": 1495,
      "11": 1496,
      "12": 1496,
      "15": 1496,
      "16": 1495,
      "18": 1495,
      "19": 1495,
      "22": 1489,
      "23": 1489,
      "24": 1488,
      "25": 1488,
      "26": 1488
    }
  },
  {
    "name": "Cabe Merah Keriting",
    "unit": "Rp / kg",
    "prices": {
      "1": 14277,
      "2": 14173,
      "3": 15501,
      "4": 14899,
      "5": 14594,
      "8": 14519,
      "9": 14330,
      "10": 13605,
      "11": 13752,
      "12": 13464,
      "15": 13297,
      "16": 13384,
      "18": 13763,
      "19": 13451,
      "22": 13768,
      "23": 14684,
      "24": 14659,
      "25": 14788,
      "26": 15012
    }
  },
  {
    "name": "Cabe Merah Biasa",
    "unit": "Rp / kg",
    "prices": {
      "1": 15203,
      "2": 15577,
      "3": 17030,
      "4": 16241,
      "5": 15627,
      "8": 15995,
      "9": 16429,
      "10": 14584,
      "11": 14518,
      "12": 14422,
      "15": 14421,
      "16": 14267,
      "18": 14505,
      "19": 14238,
      "22": 14663,
      "23": 15024,
      "24": 15262,
      "25": 15424,
      "26": 15630
    }
  },
  {
    "name": "Bawang Merah ",
    "unit": "Rp / kg",
    "prices": {
      "1": 20394,
      "2": 20375,
      "3": 19594,
      "4": 19496,
      "5": 19115,
      "8": 19009,
      "9": 18785,
      "10": 18317,
      "11": 18356,
      "12": 18013,
      "15": 17841,
      "16": 17269,
      "18": 17272,
      "19": 16943,
      "22": 17053,
      "23": 17151,
      "24": 16654,
      "25": 16544,
      "26": 16111
    }
  },
  {
    "name": "Ikan Teri Asin",
    "unit": "Rp / kg",
    "prices": {
      "1": 43729,
      "2": 43729,
      "3": 43870,
      "4": 43867,
      "5": 44103,
      "8": 44103,
      "9": 44059,
      "10": 44069,
      "11": 44004,
      "12": 44038,
      "15": 44066,
      "16": 43969,
      "18": 44038,
      "19": 43968,
      "22": 44057,
      "23": 44047,
      "24": 44230,
      "25": 44227,
      "26": 44049
    }
  },
  {
    "name": "Kacang Hijau",
    "unit": "Rp / kg",
    "prices": {
      "1": 16725,
      "2": 16730,
      "3": 16693,
      "4": 16698,
      "5": 16732,
      "8": 16739,
      "9": 16709,
      "10": 16701,
      "11": 16680,
      "12": 16894,
      "15": 16900,
      "16": 16905,
      "18": 16959,
      "19": 16980,
      "22": 16971,
      "23": 16978,
      "24": 16957,
      "25": 17007,
      "26": 17037
    }
  },
  {
    "name": "Kacang Tanah",
    "unit": "Rp / kg",
    "prices": {
      "1": 17221,
      "2": 17221,
      "3": 17271,
      "4": 17241,
      "5": 17289,
      "8": 17334,
      "9": 17444,
      "10": 17552,
      "11": 17595,
      "12": 17622,
      "15": 17676,
      "16": 17655,
      "18": 17611,
      "19": 17697,
      "22": 17697,
      "23": 17582,
      "24": 17573,
      "25": 17584,
      "26": 17644
    }
  },
  {
    "name": "Ketela Pohon",
    "unit": "Rp / kg",
    "prices": {
      "1": 3105,
      "2": 3105,
      "3": 3105,
      "4": 3105,
      "5": 3125,
      "8": 3125,
      "9": 3123,
      "10": 3123,
      "11": 3127,
      "12": 3127,
      "15": 3128,
      "16": 3131,
      "18": 3125,
      "19": 3196,
      "22": 3195,
      "23": 3125,
      "24": 3128,
      "25": 3144,
      "26": 3144
    }
  }
]