[
  {
    "name": "Minyak Goreng Kemasan",
    "unit": "Rp / 620ml",
    "prices": {
      "1": 14792,
      "29": 0,
      "2": 14802,
      "3": 14792,
      "4": 14790,
      "5": 14768,
      "8": 14829,
      "9": 14839,
      "10": 14901,
      "11": 14861,
      "12": 14875,
      "15": 14878,
      "16": 14885,
      "17": 14888,
      "18": 14888,
      "19": 14896,
      "22": 14887,
      "23": 14887
    }
  },
  {
    "name": "Minyak Goreng Curah",
    "unit": "Rp / kg",
    "prices": {
      "1": 11498,
      "29": 0,
      "2": 11477,
      "3": 11460,
      "4": 11461,
      "5": 11460,
      "8": 11427,
      "9": 11432,
      "10": 11439,
      "11": 11470,
      "12": 11443,
      "15": 11414,
      "16": 11418,
      "17": 11423,
      "18": 11429,
      "19": 11426,
      "22": 11418,
      "23": 11433
    }
  },
  {
    "name": "Daging Sapi",
    "unit": "Rp / kg",
    "prices": {
      "1": 100100,
      "29": 0,
      "2": 99911,
      "3": 99961,
      "4": 99961,
      "5": 99721,
      "8": 99917,
      "9": 99931,
      "10": 99870,
      "11": 99901,
      "12": 100002,
      "15": 99907,
      "16": 99886,
      "17": 99886,
      "18": 99836,
      "19": 99836,
      "22": 99785,
      "23": 99861
    }
  },
  {
    "name": "Daging Ayam Broiler",
    "unit": "Rp / kg",
    "prices": {
      "1": 31395,
      "29": 0,
      "2": 31179,
      "3": 31513,
      "4": 31599,
      "5": 31776,
      "8": 32224,
      "9": 32168,
      "10": 32210,
      "11": 32067,
      "12": 31814,
      "15": 31536,
      "16": 31243,
      "17": 31155,
      "18": 30850,
      "19": 30662,
      "22": 30242,
      "23": 29954
    }
  },
  {
    "name": "Daging Ayam Kampung",
    "unit": "Rp / kg",
    "prices": {
      "1": 60721,
      "29": 0,
      "2": 60838,
      "3": 60625,
      "4": 60633,
      "5": 60734,
      "8": 60796,
      "9": 60719,
      "10": 60993,
      "11": 60942,
      "12": 61094,
      "15": 60338,
      "16": 60929,
      "17": 60838,
      "18": 60788,
      "19": 60813,
      "22": 60939,
      "23": 60889
    }
  },
  {
    "name": "Telur Ayam Ras",
    "unit": "Rp / kg",
    "prices": {
      "1": 20752,
      "29": 0,
      "2": 20676,
      "3": 20675,
      "4": 20667,
      "5": 20685,
      "8": 20631,
      "9": 20629,
      "10": 20352,
      "11": 20339,
      "12": 20305,
      "15": 20288,
      "16": 20268,
      "17": 20242,
      "18": 20247,
      "19": 20224,
      "22": 20204,
      "23": 20183
    }
  },
  {
    "name": "Telur Ayam Kampung",
    "unit": "Rp / kg",
    "prices": {
      "1": 40710,
      "29": 0,
      "2": 40797,
      "3": 40757,
      "4": 40757,
      "5": 40733,
      "8": 40686,
      "9": 40674,
      "10": 40301,
      "11": 40263,
      "12": 40338,
      "15": 40418,
      "16": 40373,
      "17": 40297,
      "18": 40237,
      "19": 40312,
      "22": 40426,
      "23": 40426
    }
  },
  {
    "name": "Tepung Terigu",
    "unit": "Rp / kg",
    "prices": {
      "1": 8868,
      "29": 0,
      "2": 8848,
      "3": 8837,
      "4": 8827,
      "5": 8837,
      "8": 8832,
      "9": 8837,
      "10": 8833,
      "11": 8833,
      "12": 8838,
      "15": 8829,
      "16": 8866,
      "17": 8836,
      "18": 8836,
      "19": 8836,
      "22": 8864,
      "23": 8864
    }
  },
  {
    "name": "Kedelai Impor",
    "unit": "Rp / kg",
    "prices": {
      "1": 11350,
      "29": 0,
      "2": 11310,
      "3": 11367,
      "4": 11338,
      "5": 11338,
      "8": 11349,
      "9": 11349,
      "10": 11283,
      "11": 11272,
      "12": 11261,
      "15": 11236,
      "16": 11236,
      "17": 11230,
      "18": 11236,
      "19": 11236,
      "22": 11248,
      "23": 11293
    }
  },
  {
    "name": "Kedelai lokal",
    "unit": "Rp / kg",
    "prices": {
      "1": 10709,
      "29": 0,
      "2": 10797,
      "3": 10830,
      "4": 10847,
      "5": 10822,
      "8": 10847,
      "9": 10839,
      "10": 10847,
      "11": 10997,
      "12": 10984,
      "15": 10805,
      "16": 10805,
      "17": 10805,
      "18": 10818,
      "19": 10834,
      "22": 10909,
      "23": 10884
    }
  },
  {
    "name": "Beras Medium",
    "unit": "Rp / kg",
    "prices": {
      "1": 8943,
      "29": 0,
      "2": 8940,
      "3": 8943,
      "4": 8942,
      "5": 8946,
      "8": 8950,
      "9": 8949,
      "10": 8896,
      "11": 8886,
      "12": 8899,
      "15": 8909,
      "16": 8928,
      "17": 8926,
      "18": 8928,
      "19": 8928,
      "22": 8923,
      "23": 8918
    }
  },
  {
    "name": "Gula Pasir",
    "unit": "Rp / kg",
    "prices": {
      "1": 11281,
      "29": 0,
      "2": 11281,
      "3": 11263,
      "4": 11268,
      "5": 11268,
      "8": 11260,
      "9": 11240,
      "10": 11218,
      "11": 11213,
      "12": 11190,
      "15": 11189,
      "16": 11192,
      "17": 11192,
      "18": 11180,
      "19": 11180,
      "22": 11182,
      "23": 11192
    }
  },
  {
    "name": "Susu Kental Manis",
    "unit": "Rp / 397g",
    "prices": {
      "1": 10032,
      "29": 0,
      "2": 10032,
      "3": 10032,
      "4": 10032,
      "5": 10032,
      "8": 10032,
      "9": 10037,
      "10": 10037,
      "11": 10037,
      "12": 10032,
      "15": 10037,
      "16": 10037,
      "17": 10030,
      "18": 10037,
      "19": 10044,
      "22": 10044,
      "23": 10052
    }
  },
  {
    "name": "Mie Instant",
    "unit": "Rp / Bungkus",
    "prices": {
      "1": 1957,
      "29": 0,
      "2": 1958,
      "3": 1958,
      "4": 1958,
      "5": 1958,
      "8": 1959,
      "9": 1959,
      "10": 1959,
      "11": 1959,
      "12": 1959,
      "15": 1959,
      "16": 1965,
      "17": 1968,
      "18": 1968,
      "19": 1968,
      "22": 1972,
      "23": 1971
    }
  },
  {
    "name": "Cabe Merah Keriting",
    "unit": "Rp / kg",
    "prices": {
      "1": 20606,
      "29": 0,
      "2": 20900,
      "3": 21034,
      "4": 21435,
      "5": 21976,
      "8": 23083,
      "9": 23068,
      "10": 23472,
      "11": 23206,
      "12": 23187,
      "15": 23402,
      "16": 23404,
      "17": 23782,
      "18": 24306,
      "19": 24108,
      "22": 25083,
      "23": 25995
    }
  },
  {
    "name": "Cabe Merah Biasa",
    "unit": "Rp / kg",
    "prices": {
      "1": 19978,
      "29": 0,
      "2": 20034,
      "3": 20679,
      "4": 21082,
      "5": 21581,
      "8": 22207,
      "9": 22126,
      "10": 22230,
      "11": 22284,
      "12": 22548,
      "15": 23649,
      "16": 23666,
      "17": 24157,
      "18": 24407,
      "19": 24341,
      "22": 25034,
      "23": 25687
    }
  },
  {
    "name": "Bawang Merah ",
    "unit": "Rp / kg",
    "prices": {
      "1": 0,
      "29": 0,
      "2": 20696,
      "3": 20303,
      "4": 20189,
      "5": 20004,
      "8": 20030,
      "9": 20039,
      "10": 19959,
      "11": 20001,
      "12": 19853,
      "15": 19761,
      "16": 19842,
      "17": 19659,
      "18": 19806,
      "19": 19954,
      "22": 19819,
      "23": 19738
    }
  },
  {
    "name": "Ikan Teri Asin",
    "unit": "Rp / kg",
    "prices": {
      "1": 64340,
      "29": 0,
      "2": 64289,
      "3": 65011,
      "4": 65023,
      "5": 65276,
      "8": 65377,
      "9": 65541,
      "10": 65432,
      "11": 65026,
      "12": 64572,
      "15": 65533,
      "16": 65218,
      "17": 65340,
      "18": 64852,
      "19": 64852,
      "22": 64733,
      "23": 64632
    }
  },
  {
    "name": "Kacang Hijau",
    "unit": "Rp / kg",
    "prices": {
      "1": 19026,
      "29": 0,
      "2": 19047,
      "3": 19018,
      "4": 19018,
      "5": 19032,
      "8": 18976,
      "9": 19049,
      "10": 19097,
      "11": 19087,
      "12": 19081,
      "15": 18988,
      "16": 19044,
      "17": 19023,
      "18": 18983,
      "19": 19010,
      "22": 19054,
      "23": 19084
    }
  },
  {
    "name": "Kacang Tanah",
    "unit": "Rp / kg",
    "prices": {
      "1": 18790,
      "29": 0,
      "2": 18853,
      "3": 18868,
      "4": 18860,
      "5": 18783,
      "8": 18791,
      "9": 18759,
      "10": 18880,
      "11": 18820,
      "12": 18860,
      "15": 18975,
      "16": 18929,
      "17": 18909,
      "18": 18834,
      "19": 18813,
      "22": 18793,
      "23": 18864
    }
  },
  {
    "name": "Ketela Pohon",
    "unit": "Rp / kg",
    "prices": {
      "1": 5189,
      "29": 0,
      "2": 5178,
      "3": 5194,
      "4": 5194,
      "5": 5194,
      "8": 5194,
      "9": 5194,
      "10": 5194,
      "11": 5194,
      "12": 5199,
      "15": 5199,
      "16": 5209,
      "17": 5194,
      "18": 5194,
      "19": 5194,
      "22": 5194,
      "23": 5209
    }
  }
]